flask_pymemcache.py
flask_pymemcache-0.0.8.dist-info/METADATA
flask_pymemcache-0.0.8.dist-info/WHEEL
flask_pymemcache-0.0.8.dist-info/licenses/LICENSE.txt
flask_pymemcache-0.0.8.dist-info/RECORD
