Metadata-Version: 2.3
Name: Flask-PyMemcache
Version: 0.0.8
Summary: pymemcache integration for Flask
Project-URL: Homepage, https://github.com/KLab/Flask-PyMemcache
Author-email: Inada Naoki <songofacandy@gmail.com>
License-Expression: MIT
License-File: LICENSE.txt
Requires-Python: >=3.7
Requires-Dist: flask
Requires-Dist: pymemcache>=3.4.4
